ai_model_worker/__init__.py
ai_model_worker/config.py
ai_model_worker/worker/__init__.py
ai_model_worker/worker/BaseWorker.py
ai_model_worker-0.0.1.dev6.dist-info/METADATA
ai_model_worker-0.0.1.dev6.dist-info/WHEEL
ai_model_worker-0.0.1.dev6.dist-info/RECORD
